{"path":"E:\\jszn_bj\\day06\\mask_data\\000000000140.jpg","outputs":{"object":[{"name":"mask","bndbox":{"xmin":64,"ymin":92,"xmax":118,"ymax":156}},{"name":"mask","bndbox":{"xmin":122,"ymin":105,"xmax":167,"ymax":161}},{"name":"mask","bndbox":{"xmin":206,"ymin":146,"xmax":262,"ymax":209}},{"name":"mask","bndbox":{"xmin":408,"ymin":161,"xmax":462,"ymax":224}},{"name":"no_mask","bndbox":{"xmin":223,"ymin":116,"xmax":255,"ymax":148}}]},"time_labeled":1753777656335,"labeled":true,"size":{"width":500,"height":340,"depth":3}}